edgegap_database/__init__.py
edgegap_database/_async/__init__.py
edgegap_database/_async/_async_database_configuration_factory.py
edgegap_database/_async/_async_engine.py
edgegap_database/_async/_async_session.py
edgegap_database/_async/_async_session_factory.py
edgegap_database/_base.py
edgegap_database/_configuration.py
edgegap_database/_engine.py
edgegap_database/_factory.py
edgegap_database/_operator.py
edgegap_database/_session.py
edgegap_database/_session_factory.py
edgegap_database/errors/__init__.py
edgegap_database/errors/_exceptions.py
edgegap_database/errors/_factory.py
edgegap_database/models/__init__.py
edgegap_database/models/_sqlite.py
edgegap_database-1.11.12.dist-info/LICENSE
edgegap_database-1.11.12.dist-info/METADATA
edgegap_database-1.11.12.dist-info/WHEEL
edgegap_database-1.11.12.dist-info/RECORD
