Metadata-Version: 2.1
Name: edgegap-database
Version: 1.11.12
Summary: The Edgegap Database library includes various tools and helpers for interacting with Database and Migrations. It is designed for use within the Edgegap organization.
Author: Bastien Roy
Author-email: bastien@edgegap.com
Requires-Python: >=3.10,<4.0
Classifier: Programming Language :: Python :: 3
Classifier: Programming Language :: Python :: 3.10
Classifier: Programming Language :: Python :: 3.11
Classifier: Programming Language :: Python :: 3.12
Requires-Dist: aiosqlite (>=0.20.0,<0.21.0)
Requires-Dist: alembic (>=1.13.1,<2.0.0)
Requires-Dist: asyncpg (>=0.29.0,<0.30.0)
Requires-Dist: psycopg-c (>=3.1.18,<4.0.0)
Requires-Dist: psycopg2 (>=2.9.9,<3.0.0)
Requires-Dist: pydantic (>=2.7.1,<3.0.0)
Requires-Dist: sqlalchemy[asyncio] (>=2.0.31,<3.0.0)
Requires-Dist: sqlmodel (>=0.0.22,<0.0.23)
